colorize/__init__.py
colorize/colorize.py
colorama_colorize-0.0.1.dist-info/METADATA
colorama_colorize-0.0.1.dist-info/WHEEL
colorama_colorize-0.0.1.dist-info/top_level.txt
colorama_colorize-0.0.1.dist-info/RECORD
