Metadata-Version: 2.1
Name: colorama-colorize
Version: 0.0.1
Summary: Better syntax for Colorama
Home-page: UNKNOWN
Author: Rikai
Author-email: rikai@rikaisan.com
License: UNKNOWN
Keywords: python,color,easy,colorize,better
Platform: UNKNOWN
Classifier: Development Status :: 5 - Production/Stable
Classifier: Intended Audience :: Developers
Classifier: Programming Language :: Python :: 3
Classifier: Operating System :: Unix
Classifier: Operating System :: MacOS :: MacOS X
Classifier: Operating System :: Microsoft :: Windows
Requires-Dist: colorama
